README.rst
setup.py
virtualenvwrapper/__init__.py
virtualenvwrapper/codeintel.py
virtualenvwrapper_codeintel.egg-info/PKG-INFO
virtualenvwrapper_codeintel.egg-info/SOURCES.txt
virtualenvwrapper_codeintel.egg-info/dependency_links.txt
virtualenvwrapper_codeintel.egg-info/entry_points.txt
virtualenvwrapper_codeintel.egg-info/namespace_packages.txt
virtualenvwrapper_codeintel.egg-info/top_level.txt