Metadata-Version: 1.1
Name: virtualenvwrapper-codeintel
Version: 0.0.2
Summary: It creates the local configuration folder for the codeintel
Home-page: https://github.com/Xumeiquer/codeintel-local-config
Author: Jaume Martin
Author-email: UNKNOWN
License: MIT License
Platform: Any
Classifier: Development Status :: 4 - Beta
Classifier: License :: OSI Approved :: MIT License
Classifier: Programming Language :: Python
Classifier: Intended Audience :: Developers
Classifier: Environment :: Console
Requires: virtualenv
Requires: virtualenvwrapper (>=2.0)
Provides: virtualenvwrapper.codeintel
